{
  "W854": [
    "O29.1"
  ],
  "W805": [
    "T79.1",
    "Y76.2"
  ],
  "W826": [
    "W85.8",
    "Y76.2"
  ],
  "W827": [
    "W85.8",
    "Y76.2"
  ],
  "W584": [
    "W58.4"
  ],
  "W585": [
    "W58.5"
  ],
  "W294": [
    "W29.4"
  ],
  "W643": [
    "W04.2"
  ],
  "V364": [
    "V36.3"
  ],
  "V353": [
    "V35.3"
  ],
  "V354": [
    "V35.4"
  ],
  "G223": [
    "G22.3"
  ],
  "G272": [
    "G27.2"
  ],
  "G273": [
    "G27.3"
  ],
  "G301": [
    "G30.1"
  ],
  "G302": [
    "G30.2"
  ],
  "G343": [
    "G34.3"
  ],
  "G344": [
    "G34.4"
  ],
  "G345": [
    "G34.5"
  ],
  "G481": [
    "G48.1"
  ],
  "G482": [
    "G48.2"
  ],
  "G483": [
    "G48.3"
  ],
  "G531": [
    "G53.1"
  ],
  "G532": [
    "G53.2"
  ],
  "G581": [
    "G58.1"
  ],
  "G582": [
    "G58.2"
  ],
  "J181": [
    "J18.1"
  ],
  "J182": [
    "J18.2"
  ],
  "J273": [
    "J27.3"
  ],
  "L271": [
    "L27.1"
  ],
  "L272": [
    "L27.2"
  ],
  "L283": [
    "L28.3"
  ],
  "L362": [
    "L36.2"
  ],
  "L363": [
    "L36.3"
  ],
  "M611": [
    "M61.1"
  ],
  "M612": [
    "M61.2"
  ],
  "M651": [
    "M65.1"
  ],
  "M421": [
    "M42.1"
  ],
  "Q071": [
    "Q07.1"
  ],
  "Q072": [
    "Q07.2"
  ],
  "Q073": [
    "Q07.3"
  ],
  "Q101": [
    "Q10.1"
  ],
  "Q182": [
    "Q18.2"
  ],
  "Q183": [
    "Q18.3"
  ],
  "P221": [
    "P22.1"
  ],
  "P222": [
    "P22.2"
  ],
  "P223": [
    "P22.3"
  ],
  "P241": [
    "P24.1"
  ],
  "P242": [
    "P24.2"
  ],
  "R171": [
    "R17.1"
  ],
  "R172": [
    "R17.2"
  ],
  "R251": [
    "R25.1"
  ],
  "R252": [
    "R25.2"
  ],
  "B271": [
    "B27.1"
  ],
  "B272": [
    "B27.2"
  ],
  "B281": [
    "B28.1"
  ],
  "B291": [
    "B29.1"
  ],
  "B292": [
    "B29.2"
  ],
  "S481": [
    "S48.1"
  ],
  "S482": [
    "S48.2"
  ],
  "S491": [
    "S49.1"
  ],
  "E201": [
    "E20.1"
  ],
  "E202": [
    "E20.2"
  ],
  "E203": [
    "E20.3"
  ],
  "E041": [
    "E04.1"
  ],
  "E421": [
    "E42.1"
  ],
  "E422": [
    "E42.2"
  ],
  "E501": [
    "E50.1"
  ],
  "E502": [
    "E50.2"
  ],
  "C711": [
    "C71.1"
  ],
  "C722": [
    "C72.2"
  ],
  "C751": [
    "C75.1"
  ],
  "W371": [
    "W38.1"
  ],
  "W381": [
    "W37.1"
  ],
  "W391": [
    "W39.1"
  ],
  "W931": [
    "W93.1"
  ],
  "W401": [
    "W40.1"
  ],
  "W411": [
    "W41.1"
  ],
  "W421": [
    "W42.1"
  ],
  "W192": [
    "W19.2"
  ],
  "A051": [
    "A05.1"
  ],
  "V091": [
    "V09.1"
  ],
  "V092": [
    "V09.2"
  ],
  "V381": [
    "V38.1"
  ],
  "V382": [
    "V38.2"
  ],
  "V383": [
    "V38.3"
  ],
  "V384": [
    "V38.4"
  ]
}